fogledger/__init__.py
fogledger/indy/IndyBasic.py
fogledger/indy/Node.py
fogledger/indy/__init__.py
fogledger/iota/IotaBasic.py
fogledger/iota/__init__.py
fogledger/iota/config/ApiConfig.py
fogledger/iota/config/CoordConfig.py
fogledger/iota/config/NodeConfig.py
fogledger/iota/config/SpammerConfig.py
fogledger/iota/config/WebAppConfig.py
fogledger/iota/config/__init__.py
fogledger/iota/data/api.config.local.json
fogledger/iota/data/config-coo.json
fogledger/iota/data/config-node.json
fogledger/iota/data/config-spammer.json
fogledger/iota/data/private-network.json
fogledger/iota/data/private-tangle.sh
fogledger/iota/data/utils.sh
fogledger/iota/data/webapp.config.local.json
fogLedger-2.1.1.dist-info/LICENSE.txt
fogLedger-2.1.1.dist-info/METADATA
fogLedger-2.1.1.dist-info/WHEEL
fogLedger-2.1.1.dist-info/top_level.txt
fogLedger-2.1.1.dist-info/RECORD
