Metadata-Version: 2.1
Name: fogLedger
Version: 2.1.1
Summary: Plugin to build DLTs in Fogbed.
Home-page: https://github.com/larsid/FogLedger/tree/v2.0.0
Author: Matheus Nascimento
Author-email: matheusnascimentoti99@gmail.com
Keywords: networking,emulator,protocol,Internet,dlt,indy,fog
Classifier: Programming Language :: Python :: 3
Classifier: License :: OSI Approved :: MIT License
Classifier: Operating System :: POSIX :: Linux
Classifier: Topic :: Software Development :: Testing
Classifier: Topic :: System :: Emulators
License-File: LICENSE.txt
Requires-Dist: numpy >=1.24.2
